dfk_contracts/DFK_ABIS.json
dfk_contracts/abi_contract_wrapper.py
dfk_contracts/abi_multi_contract_wrapper.py
dfk_contracts/all_dfk_contracts.py
dfk_contracts/contracts/airdrop_claim.py
dfk_contracts/contracts/alchemist.py
dfk_contracts/contracts/assisting_auction.py
dfk_contracts/contracts/atonement_crystal.py
dfk_contracts/contracts/banker.py
dfk_contracts/contracts/birthday_cake.py
dfk_contracts/contracts/charity_fund.py
dfk_contracts/contracts/crystal_core.py
dfk_contracts/contracts/dark_summoning.py
dfk_contracts/contracts/dfk_duel_s2.py
dfk_contracts/contracts/duel_rank_claim.py
dfk_contracts/contracts/erc20.py
dfk_contracts/contracts/flag_storage_v2.py
dfk_contracts/contracts/gen0_airdrop.py
dfk_contracts/contracts/gen0_reroll.py
dfk_contracts/contracts/gene_reroll.py
dfk_contracts/contracts/hero_auction.py
dfk_contracts/contracts/hero_bridge.py
dfk_contracts/contracts/hero_core.py
dfk_contracts/contracts/hero_summoning.py
dfk_contracts/contracts/item_bridge.py
dfk_contracts/contracts/item_consumer.py
dfk_contracts/contracts/item_gold_trader_v2.py
dfk_contracts/contracts/jewel_token.py
dfk_contracts/contracts/land_auction.py
dfk_contracts/contracts/land_core.py
dfk_contracts/contracts/master_gardener.py
dfk_contracts/contracts/meditation_circle.py
dfk_contracts/contracts/multicall3.py
dfk_contracts/contracts/pasture.py
dfk_contracts/contracts/pet_auction.py
dfk_contracts/contracts/pet_bridge.py
dfk_contracts/contracts/pet_core.py
dfk_contracts/contracts/pet_exchange.py
dfk_contracts/contracts/pet_hatching.py
dfk_contracts/contracts/power_token.py
dfk_contracts/contracts/power_up_manager.py
dfk_contracts/contracts/profiles.py
dfk_contracts/contracts/quest_core.py
dfk_contracts/contracts/raffle_master.py
dfk_contracts/contracts/raffle_ticket.py
dfk_contracts/contracts/stone_carver.py
dfk_contracts/contracts/stylist.py
dfk_contracts/contracts/token_disburse.py
dfk_contracts/contracts/uniswap_v2_factory.py
dfk_contracts/contracts/uniswap_v2_router.py
dfk_contracts-0.1.7.dist-info/METADATA
dfk_contracts-0.1.7.dist-info/WHEEL
dfk_contracts-0.1.7.dist-info/RECORD
