Metadata-Version: 2.1
Name: dfk-contracts
Version: 0.1.7
Summary: Autogenerated Python wrapper for Defi Kingdoms Web3 contracts
Author: Athiriyya
Author-email: athiriyya@gmail.com
Requires-Python: >=3.10,<4.0
Classifier: Programming Language :: Python :: 3
Classifier: Programming Language :: Python :: 3.10
Classifier: Programming Language :: Python :: 3.11
Requires-Dist: web3 (>=6.2.0,<7.0.0)
